nanohub_uidl-0.2.0.data/data/etc/jupyter/jupyter_notebook_config.d/nanohubuidl.json
nanohubuidl/__init__.py
nanohubuidl/_version.py
nanohubuidl/app.py
nanohubuidl/application.py
nanohubuidl/handlers.py
nanohubuidl/ipywidgets.py
nanohubuidl/material.py
nanohubuidl/nanohub.py
nanohubuidl/plotly.py
nanohubuidl/jupyter-config/jupyter_server_config.d/nanohubuidl.json
nanohubuidl/rappture/__init__.py
nanohubuidl/rappture/builder.py
nanohubuidl/rappture/dom.py
nanohubuidl/rappture/loader.py
nanohubuidl/rappture/plot_advanced.py
nanohubuidl/rappture/plot_basics.py
nanohubuidl/rappture/science_advanced.py
nanohubuidl/rappture/science_basics.py
nanohubuidl/rappture/tool.py
nanohubuidl/teleport/__init__.py
nanohubuidl/teleport/components.py
nanohubuidl/teleport/core.py
nanohubuidl/teleport/elements.py
nanohubuidl/teleport/logic.py
nanohubuidl/teleport/utils.py
nanohub_uidl-0.2.0.dist-info/METADATA
nanohub_uidl-0.2.0.dist-info/WHEEL
nanohub_uidl-0.2.0.dist-info/entry_points.txt
nanohub_uidl-0.2.0.dist-info/top_level.txt
nanohub_uidl-0.2.0.dist-info/RECORD
