Metadata-Version: 2.4
Name: nanohub-uidl
Version: 0.2.0
Summary: A set of tools to run create Javascript Apps, using Teleporthq UIDL schema
Home-page: https://github.com/denphi/nanohub-uidl
Author: Nanohub
Author-email: denphi@denphi.com
License: BSD
Keywords: IPython
Platform: Linux
Platform: Mac OS X
Platform: Windows
Classifier: Intended Audience :: Developers
Classifier: Intended Audience :: Science/Research
Classifier: License :: OSI Approved :: BSD License
Classifier: Programming Language :: Python
Classifier: Programming Language :: Python :: 3
Classifier: Programming Language :: Python :: 3.4
Classifier: Programming Language :: Python :: 3.5
Classifier: Programming Language :: Python :: 3.6
Classifier: Framework :: Jupyter
Requires-Dist: nanohub-remote>=0.1.0
Requires-Dist: simtool
Requires-Dist: jupyter_server
Requires-Dist: notebook>=7
Requires-Dist: ipywidgets<9,>=8.0.0
Provides-Extra: test
Provides-Extra: examples
Provides-Extra: docs
Dynamic: author
Dynamic: author-email
Dynamic: classifier
Dynamic: description
Dynamic: description-content-type
Dynamic: home-page
Dynamic: keywords
Dynamic: license
Dynamic: platform
Dynamic: provides-extra
Dynamic: requires-dist
Dynamic: summary
